README.txt
setup.cfg
setup.py
docs/HISTORY.txt
docs/INSTALL.txt
docs/LICENSE.txt
jalon/__init__.py
jalon.apogee.egg-info/PKG-INFO
jalon.apogee.egg-info/SOURCES.txt
jalon.apogee.egg-info/dependency_links.txt
jalon.apogee.egg-info/entry_points.txt
jalon.apogee.egg-info/namespace_packages.txt
jalon.apogee.egg-info/not-zip-safe
jalon.apogee.egg-info/paster_plugins.txt
jalon.apogee.egg-info/requires.txt
jalon.apogee.egg-info/top_level.txt
jalon/apogee/__init__.py
jalon/apogee/configure.zcml
jalon/apogee/exportimport.py
jalon/apogee/profiles.zcml
jalon/apogee/setuphandlers.py
jalon/apogee/tests.py
jalon/apogee/utility.py
jalon/apogee/browser/__init__.py
jalon/apogee/browser/browser.py
jalon/apogee/browser/configure.zcml
jalon/apogee/browser/controlpanel.py
jalon/apogee/browser/images/apogee_icon.gif
jalon/apogee/browser/interfaces/__init__.py
jalon/apogee/browser/interfaces/browser.py
jalon/apogee/browser/interfaces/controlpanel.py
jalon/apogee/interfaces/__init__.py
jalon/apogee/interfaces/utility.py
jalon/apogee/profiles/default/actionicons.xml
jalon/apogee/profiles/default/apogee.xml
jalon/apogee/profiles/default/componentregistry.xml
jalon/apogee/profiles/default/controlpanel.xml
jalon/apogee/profiles/default/metadata.xml
jalon/apogee/profiles/default/portal-apogee.txt
jalon/apogee/profiles/default/toolset.xml
jalon/apogee/tables/__init__.py
jalon/apogee/tables/elementpedagogi.py
jalon/apogee/tables/elpregroupeelp.py
jalon/apogee/tables/gpeobj.py
jalon/apogee/tables/groupe.py
jalon/apogee/tables/indaffectegpe.py
jalon/apogee/tables/indcontratelp.py
jalon/apogee/tables/individu.py
jalon/apogee/tables/insadmetp.py
jalon/apogee/tables/vdifractionnervet.py
jalon/apogee/tables/versionetape.py