Metadata-Version: 1.0
Name: jalon.apogee
Version: 1.3.1r16
Summary: Un connecteur apogee pour Jalon
Home-page: http://unice.fr
Author: Bordonado Christophe (Université Nice Sophia Antipolis Service TICE)
Author-email: tice@unice.fr
License: UNKNOWN
Platform: UNKNOWN
Classifier: Framework :: Plone
Classifier: Programming Language :: Python
